__init__.py
scalable_softmax.py
scalable_softmax-0.1.5.dist-info/licenses/LICENSE
scalable_softmax-0.1.5.dist-info/METADATA
scalable_softmax-0.1.5.dist-info/WHEEL
scalable_softmax-0.1.5.dist-info/top_level.txt
scalable_softmax-0.1.5.dist-info/RECORD
