Metadata-Version: 2.4
Name: scalable_softmax
Version: 0.1.5
Summary: PyTorch implementation of Scalable-Softmax for attention mechanisms
Author-email: Greg DeVosNouri <gdevos010@gamil.com>
License: MIT License
Project-URL: Homepage, https://pypi.org/project/scalable-softmax/
Project-URL: Repository, https://github.com/gdevos010/Scalable-Softmax
Keywords: pytorch,deep-learning,attention,transformer
Classifier: Development Status :: 4 - Beta
Classifier: Intended Audience :: Developers
Classifier: Topic :: Scientific/Engineering :: Artificial Intelligence
Classifier: License :: OSI Approved :: MIT License
Classifier: Programming Language :: Python :: 3.9
Requires-Python: >=3.9
License-File: LICENSE
Requires-Dist: torch>=1.8
Requires-Dist: numpy>=1.23.5
Provides-Extra: dev
Requires-Dist: ruff; extra == "dev"
Requires-Dist: build; extra == "dev"
Requires-Dist: twine; extra == "dev"
Dynamic: license-file
